trellis_mcp/__init__.py
trellis_mcp/backlog_loader.py
trellis_mcp/claim_next_task.py
trellis_mcp/cli.py
trellis_mcp/complete_task.py
trellis_mcp/dependency_resolver.py
trellis_mcp/filters.py
trellis_mcp/fs_utils.py
trellis_mcp/graph_utils.py
trellis_mcp/id_utils.py
trellis_mcp/io_utils.py
trellis_mcp/json_rpc_logging_middleware.py
trellis_mcp/loader.py
trellis_mcp/log_filename.py
trellis_mcp/logger.py
trellis_mcp/markdown_loader.py
trellis_mcp/object_dumper.py
trellis_mcp/object_parser.py
trellis_mcp/path_resolver.py
trellis_mcp/prune_logs.py
trellis_mcp/query.py
trellis_mcp/rfc3339_timestamp.py
trellis_mcp/scanner.py
trellis_mcp/server.py
trellis_mcp/settings.py
trellis_mcp/task_sorter.py
trellis_mcp/validation.py
trellis_mcp/exceptions/__init__.py
trellis_mcp/exceptions/cascade_error.py
trellis_mcp/exceptions/invalid_status_for_completion.py
trellis_mcp/exceptions/no_available_task.py
trellis_mcp/exceptions/prerequisites_not_complete.py
trellis_mcp/exceptions/protected_object_error.py
trellis_mcp/models/__init__.py
trellis_mcp/models/common.py
trellis_mcp/models/filter_params.py
trellis_mcp/models/priority_ranking.py
trellis_mcp/models/task_sort_key.py
trellis_mcp/schema/__init__.py
trellis_mcp/schema/base.py
trellis_mcp/schema/base_schema.py
trellis_mcp/schema/epic.py
trellis_mcp/schema/feature.py
trellis_mcp/schema/kind_enum.py
trellis_mcp/schema/project.py
trellis_mcp/schema/status_enum.py
trellis_mcp/schema/task.py
trellis_mcp/tools/__init__.py
trellis_mcp/tools/claim_next_task.py
trellis_mcp/tools/complete_task.py
trellis_mcp/tools/create_object.py
trellis_mcp/tools/get_next_reviewable_task.py
trellis_mcp/tools/get_object.py
trellis_mcp/tools/health_check.py
trellis_mcp/tools/list_backlog.py
trellis_mcp/tools/update_object.py
task_trellis_mcp-1.0.1rc10.dist-info/METADATA
task_trellis_mcp-1.0.1rc10.dist-info/WHEEL
task_trellis_mcp-1.0.1rc10.dist-info/entry_points.txt
task_trellis_mcp-1.0.1rc10.dist-info/top_level.txt
task_trellis_mcp-1.0.1rc10.dist-info/RECORD
