Metadata-Version: 2.4
Name: task-trellis-mcp
Version: 1.0.1rc10
Summary: File-backed MCP server for hierarchical project management (Projects → Epics → Features → Tasks)
Author: Lang Adventure LLC
License: MIT
Project-URL: Homepage, https://github.com/langadventurellc/trellis-mcp
Project-URL: Repository, https://github.com/langadventurellc/trellis-mcp
Project-URL: Issues, https://github.com/langadventurellc/trellis-mcp/issues
Keywords: mcp,project-management,planning,tasks,development
Classifier: Development Status :: 3 - Alpha
Classifier: Intended Audience :: Developers
Classifier: License :: OSI Approved :: MIT License
Classifier: Programming Language :: Python :: 3
Classifier: Programming Language :: Python :: 3.12
Classifier: Topic :: Software Development :: Libraries :: Python Modules
Classifier: Topic :: Office/Business :: Scheduling
Requires-Python: >=3.12
Requires-Dist: click>=8.1
Requires-Dist: fastmcp>=2.10.5
Requires-Dist: httpx<1.0.0,>=0.24.0
Requires-Dist: pydantic-settings>=2.0.0
Requires-Dist: python-slugify>=8.0.4
Requires-Dist: PyYAML>=6.0
Provides-Extra: dev
Requires-Dist: black; extra == "dev"
Requires-Dist: flake8; extra == "dev"
Requires-Dist: flake8-pyproject; extra == "dev"
Requires-Dist: freezegun>=1.5.3; extra == "dev"
Requires-Dist: isort; extra == "dev"
Requires-Dist: pyright; extra == "dev"
Requires-Dist: pytest; extra == "dev"
Requires-Dist: pytest-asyncio; extra == "dev"
Requires-Dist: pytest-cov; extra == "dev"
Requires-Dist: pre-commit; extra == "dev"
